aliyun_sdk/__init__.py
aliyun_sdk/client.py
aliyun_sdk/common.py
aliyun_sdk/oss.py
zy_aliyun_python_sdk-0.1.6.dist-info/LICENSE
zy_aliyun_python_sdk-0.1.6.dist-info/METADATA
zy_aliyun_python_sdk-0.1.6.dist-info/WHEEL
zy_aliyun_python_sdk-0.1.6.dist-info/top_level.txt
zy_aliyun_python_sdk-0.1.6.dist-info/RECORD
