Metadata-Version: 2.1
Name: zy-aliyun-python-sdk
Version: 0.1.6
Summary: sdk for aliyun
Home-page: https://github.com/johntoms/aliyun-sdk
Author: JohnToms
Author-email: johntoms@163.com
License: MIT
Platform: UNKNOWN
Classifier: Programming Language :: Python :: 3
Classifier: License :: OSI Approved :: MIT License
Classifier: Operating System :: OS Independent
Requires-Dist: certifi (>=2019.6.16)
Requires-Dist: chardet (>=3.0.4)
Requires-Dist: decorator (>=4.4.0)
Requires-Dist: idna (>=2.8)
Requires-Dist: requests (>=2.22.0)
Requires-Dist: retry (>=0.9.2)
Requires-Dist: urllib3 (>=1.25.3)
Requires-Dist: xmltodict (>=0.12.0)
